asyncro/__init__.py
asyncro/asyncro.py
asyncro-0.0.1.dist-info/METADATA
asyncro-0.0.1.dist-info/WHEEL
asyncro-0.0.1.dist-info/top_level.txt
asyncro-0.0.1.dist-info/RECORD
