Metadata-Version: 2.1
Name: asyncro
Version: 0.0.1
Summary: Simple async module based on threading.
Home-page: https://github.com/fladegh/asyncflow
Author: justflade & nekit270
Author-email: apbclub142@gmail.com
License: UNKNOWN
Project-URL: GitHub, https://github.com/fladegh/asyncflow
Keywords: async thread threads
Platform: UNKNOWN
Classifier: Programming Language :: Python :: 3.8
Classifier: License :: OSI Approved :: MIT License
Classifier: Operating System :: OS Independent
Requires-Python: >=3.8
